Metadata-Version: 2.1
Name: AIParcialUPC
Version: 0.3
Summary: Esta es la descripcion de mi paquete
Author: XD
License: MIT
Keywords: perceptron,ramificacion,ai
